riscos_stronghelp/__init__.py
riscos_stronghelp/__main__.py
riscos_stronghelp/format.py
riscos_stronghelp-0.2.0.dist-info/LICENSE
riscos_stronghelp-0.2.0.dist-info/METADATA
riscos_stronghelp-0.2.0.dist-info/WHEEL
riscos_stronghelp-0.2.0.dist-info/entry_points.txt
riscos_stronghelp-0.2.0.dist-info/top_level.txt
riscos_stronghelp-0.2.0.dist-info/RECORD
