Metadata-Version: 2.1
Name: riscos-stronghelp
Version: 0.2.0
Summary: Extract RISC OS StrongHelp manuals
Home-page: https://github.com/gerph/riscos-stronghelp-python
Author: Charles Ferguson
Author-email: gerph@gerph.org
License: MIT
Keywords: riscos
Platform: UNKNOWN
Classifier: Development Status :: 4 - Beta
Classifier: Intended Audience :: Developers
Classifier: License :: OSI Approved :: MIT License
Classifier: Programming Language :: Python :: 2.7
Classifier: Programming Language :: Python :: 3
Classifier: Operating System :: OS Independent
Requires-Python: >=2.7
